anonpy/__init__.py
anonpy/__main__.py
anonpy/anonpy.py
anonpy/cli.py
anonpy/endpoint.py
anonpy/server_response.py
anonpy/internals/__init__.py
anonpy/internals/authorization.py
anonpy/internals/config_handler.py
anonpy/internals/csv_formatter.py
anonpy/internals/json_formatter.py
anonpy/internals/log_handler.py
anonpy/internals/metadata.py
anonpy/internals/request_handler.py
anonpy/internals/timeout.py
anonpy/internals/utils.py
anonpy/providers/__init__.py
anonpy/providers/pixeldrain.py
anonpy/security/__init__.py
anonpy/security/asymmetric.py
anonpy/security/hashes.py
anonpy/security/random.py
anonpy/security/security_warning.py
anonpy/security/symmetric.py
anonpy-1.0.0.dist-info/LICENSE
anonpy-1.0.0.dist-info/METADATA
anonpy-1.0.0.dist-info/WHEEL
anonpy-1.0.0.dist-info/entry_points.txt
anonpy-1.0.0.dist-info/top_level.txt
anonpy-1.0.0.dist-info/RECORD
