Metadata-Version: 2.1
Name: anonpy
Version: 1.0.0
Summary: A slick and modern Python package for anonymous file sharing
Home-page: https://github.com/advanced-systems/anonpy
Author: Stefan Greve
Author-email: greve.stefan@outlook.jp
Maintainer: Stefan Greve
Maintainer-email: greve.stefan@outlook.jp
License: MIT
Project-URL: Source Code, https://github.com/advanced-systems/anonpy
Project-URL: Bug Reports, https://github.com/advanced-systems/anonpy/issues
Project-URL: Documentation, https://github.com/advanced-systems/anonpy/wiki
Project-URL: Changelog, https://github.com/advanced-systems/anonpy/blob/master/README.md
Keywords: advanced systems anonpy rest api anonymous file sharing
Classifier: Programming Language :: Python :: 3.12
Classifier: Intended Audience :: Developers
Classifier: Natural Language :: English
Classifier: Topic :: Internet :: WWW/HTTP :: Dynamic Content
Classifier: Topic :: Software Development :: Libraries
Classifier: Topic :: Utilities
Classifier: License :: OSI Approved :: MIT License
Classifier: Operating System :: OS Independent
Requires-Python: >=3.12
License-File: LICENSE
Requires-Dist: cryptography ==41.0.4
Requires-Dist: requests ==2.31.0
Requires-Dist: rich ==13.6.0
